pebble_shell/__init__.py
pebble_shell/__main__.py
pebble_shell/shell.py
pebble_shell/commands/__init__.py
pebble_shell/commands/_base.py
pebble_shell/commands/advanced_utils/__init__.py
pebble_shell/commands/advanced_utils/brackettest.py
pebble_shell/commands/advanced_utils/doublebrackettest.py
pebble_shell/commands/advanced_utils/hostid.py
pebble_shell/commands/advanced_utils/less.py
pebble_shell/commands/advanced_utils/logger.py
pebble_shell/commands/advanced_utils/more.py
pebble_shell/commands/advanced_utils/patch.py
pebble_shell/commands/advanced_utils/pidof.py
pebble_shell/commands/advanced_utils/pstrace.py
pebble_shell/commands/advanced_utils/tee.py
pebble_shell/commands/advanced_utils/test.py
pebble_shell/commands/advanced_utils/xargs.py
pebble_shell/commands/advanced_utils/yes.py
pebble_shell/commands/builtin/__init__.py
pebble_shell/commands/builtin/_base.py
pebble_shell/commands/builtin/alias.py
pebble_shell/commands/builtin/beep.py
pebble_shell/commands/builtin/bzcat.py
pebble_shell/commands/builtin/cal.py
pebble_shell/commands/builtin/cd.py
pebble_shell/commands/builtin/cut.py
pebble_shell/commands/builtin/date.py
pebble_shell/commands/builtin/echo.py
pebble_shell/commands/builtin/edit.py
pebble_shell/commands/builtin/env.py
pebble_shell/commands/builtin/false.py
pebble_shell/commands/builtin/grep.py
pebble_shell/commands/builtin/hd.py
pebble_shell/commands/builtin/hexdump.py
pebble_shell/commands/builtin/history.py
pebble_shell/commands/builtin/id.py
pebble_shell/commands/builtin/info.py
pebble_shell/commands/builtin/jq.py
pebble_shell/commands/builtin/lsof.py
pebble_shell/commands/builtin/markdown.py
pebble_shell/commands/builtin/md5sum.py
pebble_shell/commands/builtin/mkpasswd.py
pebble_shell/commands/builtin/pebblesay.py
pebble_shell/commands/builtin/printenv.py
pebble_shell/commands/builtin/printf.py
pebble_shell/commands/builtin/pwd.py
pebble_shell/commands/builtin/sha1sum.py
pebble_shell/commands/builtin/sha256sum.py
pebble_cascade-1.0.0a7.dist-info/METADATA
pebble_cascade-1.0.0a7.dist-info/WHEEL
pebble_cascade-1.0.0a7.dist-info/entry_points.txt
pebble_cascade-1.0.0a7.dist-info/RECORD
