Metadata-Version: 2.4
Name: pebble-cascade
Version: 1.0.0a7
Summary: A shell for debugging containers, particularly bare rocks, using Pebble
Project-URL: Homepage, https://github.com/tonyandrewmeyer/cascade
Project-URL: Repository, https://github.com/tonyandrewmeyer/cascade
Project-URL: Issues, https://github.com/tonyandrewmeyer/cascade/issues
Author-email: Tony Meyer <cascade@aotearoa.dev>
License: MIT
Classifier: Development Status :: 3 - Alpha
Classifier: Intended Audience :: Developers
Classifier: License :: OSI Approved :: MIT License
Classifier: Programming Language :: Python :: 3
Classifier: Programming Language :: Python :: 3.8
Classifier: Programming Language :: Python :: 3.9
Classifier: Programming Language :: Python :: 3.10
Classifier: Programming Language :: Python :: 3.11
Classifier: Programming Language :: Python :: 3.12
Requires-Python: >=3.11
Requires-Dist: ops<4,>=2.0.0
Requires-Dist: pebble-shimmer
Requires-Dist: rich~=13.7
Requires-Dist: typer~=0.16
Provides-Extra: dev
Requires-Dist: pre-commit>=3.0.0; extra == 'dev'
Requires-Dist: pyright>=1.1.0; extra == 'dev'
Requires-Dist: pytest-cov>=4.0.0; extra == 'dev'
Requires-Dist: pytest-mock>=3.10.0; extra == 'dev'
Requires-Dist: pytest>=7.0.0; extra == 'dev'
Requires-Dist: ruff>=0.1.0; extra == 'dev'
Requires-Dist: tox>=4.0.0; extra == 'dev'
